Metadata-Version: 1.0
Name: codbot
Version: 0.2
Summary: The deploy bot
Home-page: http://github.com/deploybot
Author: AN
Author-email: an@g.com
License: MIT
Platform: UNKNOWN
